text_classify/__init__.py
text_classify/classify.py
text_classify/cnn.py
text_classify/config.py
text_classify/mcnn.py
text_classify/mgcnn.py
text_classify/simple_cnn.py
text_classify/utils.py
text_classify-0.0.8.dist-info/DESCRIPTION.rst
text_classify-0.0.8.dist-info/METADATA
text_classify-0.0.8.dist-info/RECORD
text_classify-0.0.8.dist-info/WHEEL
text_classify-0.0.8.dist-info/metadata.json
text_classify-0.0.8.dist-info/top_level.txt
