Metadata-Version: 2.0
Name: text-classify
Version: 0.0.8
Summary: Simple tool to predict text classes with various models.
Home-page: UNKNOWN
Author: UNKNOWN
Author-email: UNKNOWN
License: MIT
Platform: UNKNOWN
Requires-Dist: jieba
Requires-Dist: numpy
Requires-Dist: plane
Requires-Dist: pybind11
Requires-Dist: pyltp
Requires-Dist: scipy
